{
  "contract": "0xa4ebb48e4378e6f771b7f857623298bdb50c11b1",
  "tool": "smartcheck",
  "start": 1563755325.5259666,
  "end": 1563755332.1172967,
  "duration": 6.591330051422119,
  "analysis": [
    {
      "name": "SOLIDITY_PRAGMAS_VERSION",
      "patternId": "23fc32",
      "severity": 1,
      "line": 10,
      "column": 16,
      "content": "^"
    },
    {
      "name": "SOLIDITY_UPGRADE_TO_050",
      "patternId": "341gim",
      "severity": 1,
      "line": 19,
      "column": 45,
      "content": "string"
    },
    {
      "name": "SOLIDITY_UPGRADE_TO_050",
      "patternId": "341gim",
      "severity": 1,
      "line": 23,
      "column": 28,
      "content": "stringgreeting"
    },
    {
      "name": "SOLIDITY_VISIBILITY",
      "patternId": "b51ce0",
      "severity": 1,
      "line": 17,
      "column": 4,
      "content": "stringinput=\"Hello world.\";"
    }
  ]
}