{
  "contract": "0xb87525c0de1d58264b55f7db04cbf5a5f7481b87",
  "tool": "slither",
  "start": 1563625053.4028797,
  "end": 1563625057.130116,
  "duration": 3.727236270904541,
  "analysis": [
    {
      "check": "constable-states",
      "impact": "Informational",
      "confidence": "High",
      "description": "CatCoin.decimals should be constant (/unique_chucks/24/0xb87525c0de1d58264b55f7db04cbf5a5f7481b87.sol#42-43)\nCatCoin.name should be constant (/unique_chucks/24/0xb87525c0de1d58264b55f7db04cbf5a5f7481b87.sol#39-40)\nCatCoin.symbol should be constant (/unique_chucks/24/0xb87525c0de1d58264b55f7db04cbf5a5f7481b87.sol#40-42)\n",
      "elements": [
        {
          "type": "variable",
          "name": "decimals",
          "source_mapping": {
            "start": 1257,
            "length": 26,
            "filename": "/unique_chucks/24/0xb87525c0de1d58264b55f7db04cbf5a5f7481b87.sol",
            "lines": [
              42,
              43
            ]
          }
        },
        {
          "type": "variable",
          "name": "name",
          "source_mapping": {
            "start": 1176,
            "length": 38,
            "filename": "/unique_chucks/24/0xb87525c0de1d58264b55f7db04cbf5a5f7481b87.sol",
            "lines": [
              39,
              40
            ]
          }
        },
        {
          "type": "variable",
          "name": "symbol",
          "source_mapping": {
            "start": 1221,
            "length": 29,
            "filename": "/unique_chucks/24/0xb87525c0de1d58264b55f7db04cbf5a5f7481b87.sol",
            "lines": [
              40,
              41,
              42
            ]
          }
        }
      ]
    },
    {
      "check": "external-function",
      "impact": "Informational",
      "confidence": "High",
      "description": "IERC20.totalSupply (/unique_chucks/24/0xb87525c0de1d58264b55f7db04cbf5a5f7481b87.sol#19-20) should be declared external\n",
      "elements": [
        {
          "type": "function",
          "name": "totalSupply",
          "source_mapping": {
            "start": 375,
            "length": 55,
            "filename": "/unique_chucks/24/0xb87525c0de1d58264b55f7db04cbf5a5f7481b87.sol",
            "lines": [
              19,
              20
            ]
          },
          "contract": {
            "type": "contract",
            "name": "IERC20",
            "source_mapping": {
              "start": 351,
              "length": 660,
              "filename": "/unique_chucks/24/0xb87525c0de1d58264b55f7db04cbf5a5f7481b87.sol",
              "lines": [
                18,
                19,
                20,
                21,
                22,
                23,
                24,
                25,
                26,
                27,
                28,
                29,
                30,
                31,
                32
              ]
            }
          }
        }
      ]
    },
    {
      "check": "external-function",
      "impact": "Informational",
      "confidence": "High",
      "description": "CatCoin.totalSupply (/unique_chucks/24/0xb87525c0de1d58264b55f7db04cbf5a5f7481b87.sol#168-171) should be declared external\n",
      "elements": [
        {
          "type": "function",
          "name": "totalSupply",
          "source_mapping": {
            "start": 5451,
            "length": 90,
            "filename": "/unique_chucks/24/0xb87525c0de1d58264b55f7db04cbf5a5f7481b87.sol",
            "lines": [
              168,
              169,
              170,
              171
            ]
          },
          "contract": {
            "type": "contract",
            "name": "CatCoin",
            "source_mapping": {
              "start": 1083,
              "length": 5529,
              "filename": "/unique_chucks/24/0xb87525c0de1d58264b55f7db04cbf5a5f7481b87.sol",
              "lines": [
                36,
                37,
                38,
                39,
                40,
                41,
                42,
                43,
                44,
                45,
                46,
                47,
                48,
                49,
                50,
                51,
                52,
                53,
                54,
                55,
                56,
                57,
                58,
                59,
                60,
                61,
                62,
                63,
                64,
                65,
                66,
                67,
                68,
                69,
                70,
                71,
                72,
                73,
                74,
                75,
                76,
                77,
                78,
                79,
                80,
                81,
                82,
                83,
                84,
                85,
                86,
                87,
                88,
                89,
                90,
                91,
                92,
                93,
                94,
                95,
                96,
                97,
                98,
                99,
                100,
                101,
                102,
                103,
                104,
                105,
                106,
                107,
                108,
                109,
                110,
                111,
                112,
                113,
                114,
                115,
                116,
                117,
                118,
                119,
                120,
                121,
                122,
                123,
                124,
                125,
                126,
                127,
                128,
                129,
                130,
                131,
                132,
                133,
                134,
                135,
                136,
                137,
                138,
                139,
                140,
                141,
                142,
                143,
                144,
                145,
                146,
                147,
                148,
                149,
                150,
                151,
                152,
                153,
                154,
                155,
                156,
                157,
                158,
                159,
                160,
                161,
                162,
                163,
                164,
                165,
                166,
                167,
                168,
                169,
                170,
                171,
                172,
                173,
                174,
                175,
                176,
                177,
                178,
                179,
                180,
                181,
                182,
                183,
                184,
                185,
                186,
                187,
                188,
                189,
                190,
                191,
                192,
                193,
                194,
                195,
                196,
                197,
                198
              ]
            }
          }
        }
      ]
    },
    {
      "check": "external-function",
      "impact": "Informational",
      "confidence": "High",
      "description": "IERC20.balanceOf (/unique_chucks/24/0xb87525c0de1d58264b55f7db04cbf5a5f7481b87.sol#20-21) should be declared external\n",
      "elements": [
        {
          "type": "function",
          "name": "balanceOf",
          "source_mapping": {
            "start": 436,
            "length": 64,
            "filename": "/unique_chucks/24/0xb87525c0de1d58264b55f7db04cbf5a5f7481b87.sol",
            "lines": [
              20,
              21
            ]
          },
          "contract": {
            "type": "contract",
            "name": "IERC20",
            "source_mapping": {
              "start": 351,
              "length": 660,
              "filename": "/unique_chucks/24/0xb87525c0de1d58264b55f7db04cbf5a5f7481b87.sol",
              "lines": [
                18,
                19,
                20,
                21,
                22,
                23,
                24,
                25,
                26,
                27,
                28,
                29,
                30,
                31,
                32
              ]
            }
          }
        }
      ]
    },
    {
      "check": "external-function",
      "impact": "Informational",
      "confidence": "High",
      "description": "CatCoin.balanceOf (/unique_chucks/24/0xb87525c0de1d58264b55f7db04cbf5a5f7481b87.sol#171-175) should be declared external\n",
      "elements": [
        {
          "type": "function",
          "name": "balanceOf",
          "source_mapping": {
            "start": 5549,
            "length": 101,
            "filename": "/unique_chucks/24/0xb87525c0de1d58264b55f7db04cbf5a5f7481b87.sol",
            "lines": [
              171,
              172,
              173,
              174,
              175
            ]
          },
          "contract": {
            "type": "contract",
            "name": "CatCoin",
            "source_mapping": {
              "start": 1083,
              "length": 5529,
              "filename": "/unique_chucks/24/0xb87525c0de1d58264b55f7db04cbf5a5f7481b87.sol",
              "lines": [
                36,
                37,
                38,
                39,
                40,
                41,
                42,
                43,
                44,
                45,
                46,
                47,
                48,
                49,
                50,
                51,
                52,
                53,
                54,
                55,
                56,
                57,
                58,
                59,
                60,
                61,
                62,
                63,
                64,
                65,
                66,
                67,
                68,
                69,
                70,
                71,
                72,
                73,
                74,
                75,
                76,
                77,
                78,
                79,
                80,
                81,
                82,
                83,
                84,
                85,
                86,
                87,
                88,
                89,
                90,
                91,
                92,
                93,
                94,
                95,
                96,
                97,
                98,
                99,
                100,
                101,
                102,
                103,
                104,
                105,
                106,
                107,
                108,
                109,
                110,
                111,
                112,
                113,
                114,
                115,
                116,
                117,
                118,
                119,
                120,
                121,
                122,
                123,
                124,
                125,
                126,
                127,
                128,
                129,
                130,
                131,
                132,
                133,
                134,
                135,
                136,
                137,
                138,
                139,
                140,
                141,
                142,
                143,
                144,
                145,
                146,
                147,
                148,
                149,
                150,
                151,
                152,
                153,
                154,
                155,
                156,
                157,
                158,
                159,
                160,
                161,
                162,
                163,
                164,
                165,
                166,
                167,
                168,
                169,
                170,
                171,
                172,
                173,
                174,
                175,
                176,
                177,
                178,
                179,
                180,
                181,
                182,
                183,
                184,
                185,
                186,
                187,
                188,
                189,
                190,
                191,
                192,
                193,
                194,
                195,
                196,
                197,
                198
              ]
            }
          }
        }
      ]
    },
    {
      "check": "external-function",
      "impact": "Informational",
      "confidence": "High",
      "description": "CatCoin.transfer (/unique_chucks/24/0xb87525c0de1d58264b55f7db04cbf5a5f7481b87.sol#175-188) should be declared external\n",
      "elements": [
        {
          "type": "function",
          "name": "transfer",
          "source_mapping": {
            "start": 5662,
            "length": 435,
            "filename": "/unique_chucks/24/0xb87525c0de1d58264b55f7db04cbf5a5f7481b87.sol",
            "lines": [
              175,
              176,
              177,
              178,
              179,
              180,
              181,
              182,
              183,
              184,
              185,
              186,
              187,
              188
            ]
          },
          "contract": {
            "type": "contract",
            "name": "CatCoin",
            "source_mapping": {
              "start": 1083,
              "length": 5529,
              "filename": "/unique_chucks/24/0xb87525c0de1d58264b55f7db04cbf5a5f7481b87.sol",
              "lines": [
                36,
                37,
                38,
                39,
                40,
                41,
                42,
                43,
                44,
                45,
                46,
                47,
                48,
                49,
                50,
                51,
                52,
                53,
                54,
                55,
                56,
                57,
                58,
                59,
                60,
                61,
                62,
                63,
                64,
                65,
                66,
                67,
                68,
                69,
                70,
                71,
                72,
                73,
                74,
                75,
                76,
                77,
                78,
                79,
                80,
                81,
                82,
                83,
                84,
                85,
                86,
                87,
                88,
                89,
                90,
                91,
                92,
                93,
                94,
                95,
                96,
                97,
                98,
                99,
                100,
                101,
                102,
                103,
                104,
                105,
                106,
                107,
                108,
                109,
                110,
                111,
                112,
                113,
                114,
                115,
                116,
                117,
                118,
                119,
                120,
                121,
                122,
                123,
                124,
                125,
                126,
                127,
                128,
                129,
                130,
                131,
                132,
                133,
                134,
                135,
                136,
                137,
                138,
                139,
                140,
                141,
                142,
                143,
                144,
                145,
                146,
                147,
                148,
                149,
                150,
                151,
                152,
                153,
                154,
                155,
                156,
                157,
                158,
                159,
                160,
                161,
                162,
                163,
                164,
                165,
                166,
                167,
                168,
                169,
                170,
                171,
                172,
                173,
                174,
                175,
                176,
                177,
                178,
                179,
                180,
                181,
                182,
                183,
                184,
                185,
                186,
                187,
                188,
                189,
                190,
                191,
                192,
                193,
                194,
                195,
                196,
                197,
                198
              ]
            }
          }
        }
      ]
    },
    {
      "check": "external-function",
      "impact": "Informational",
      "confidence": "High",
      "description": "IERC20.transfer (/unique_chucks/24/0xb87525c0de1d58264b55f7db04cbf5a5f7481b87.sol#21-22) should be declared external\n",
      "elements": [
        {
          "type": "function",
          "name": "transfer",
          "source_mapping": {
            "start": 506,
            "length": 69,
            "filename": "/unique_chucks/24/0xb87525c0de1d58264b55f7db04cbf5a5f7481b87.sol",
            "lines": [
              21,
              22
            ]
          },
          "contract": {
            "type": "contract",
            "name": "IERC20",
            "source_mapping": {
              "start": 351,
              "length": 660,
              "filename": "/unique_chucks/24/0xb87525c0de1d58264b55f7db04cbf5a5f7481b87.sol",
              "lines": [
                18,
                19,
                20,
                21,
                22,
                23,
                24,
                25,
                26,
                27,
                28,
                29,
                30,
                31,
                32
              ]
            }
          }
        }
      ]
    },
    {
      "check": "naming-convention",
      "impact": "Informational",
      "confidence": "High",
      "description": "Variable 'CatCoin.VaultName' (/unique_chucks/24/0xb87525c0de1d58264b55f7db04cbf5a5f7481b87.sol#50-53) is not in mixedCase\n",
      "elements": [
        {
          "target": "variable",
          "convention": "mixedCase",
          "name": "VaultName",
          "source_mapping": {
            "start": 1528,
            "length": 63,
            "filename": "/unique_chucks/24/0xb87525c0de1d58264b55f7db04cbf5a5f7481b87.sol",
            "lines": [
              50,
              51,
              52,
              53
            ]
          }
        }
      ]
    }
  ]
}