{
  "contract": "0xc1746273c53b9bf2d827b01b3974113bb597eaeb",
  "tool": "solhint",
  "start": 1563753583.0081828,
  "end": 1563753586.6641228,
  "duration": 3.655940055847168,
  "analysis": [
    {
      "file": "/unique_chucks/41/0xc1746273c53b9bf2d827b01b3974113bb597eaeb.sol",
      "line": "4",
      "column": "3",
      "message": "Expected indentation of 4 spaces but found 2",
      "level": "Error",
      "type": "indent"
    },
    {
      "file": "/unique_chucks/41/0xc1746273c53b9bf2d827b01b3974113bb597eaeb.sol",
      "line": "5",
      "column": "3",
      "message": "Expected indentation of 4 spaces but found 2",
      "level": "Error",
      "type": "indent"
    },
    {
      "file": "/unique_chucks/41/0xc1746273c53b9bf2d827b01b3974113bb597eaeb.sol",
      "line": "6",
      "column": "3",
      "message": "Expected indentation of 4 spaces but found 2",
      "level": "Error",
      "type": "indent"
    },
    {
      "file": "/unique_chucks/41/0xc1746273c53b9bf2d827b01b3974113bb597eaeb.sol",
      "line": "7",
      "column": "3",
      "message": "Expected indentation of 4 spaces but found 2",
      "level": "Error",
      "type": "indent"
    },
    {
      "file": "/unique_chucks/41/0xc1746273c53b9bf2d827b01b3974113bb597eaeb.sol",
      "line": "8",
      "column": "3",
      "message": "Expected indentation of 4 spaces but found 2",
      "level": "Error",
      "type": "indent"
    },
    {
      "file": "/unique_chucks/41/0xc1746273c53b9bf2d827b01b3974113bb597eaeb.sol",
      "line": "10",
      "column": "3",
      "message": "Expected indentation of 4 spaces but found 2",
      "level": "Error",
      "type": "indent"
    },
    {
      "file": "/unique_chucks/41/0xc1746273c53b9bf2d827b01b3974113bb597eaeb.sol",
      "line": "11",
      "column": "3",
      "message": "Expected indentation of 4 spaces but found 2",
      "level": "Error",
      "type": "indent"
    },
    {
      "file": "/unique_chucks/41/0xc1746273c53b9bf2d827b01b3974113bb597eaeb.sol",
      "line": "13",
      "column": "3",
      "message": "Expected indentation of 4 spaces but found 2",
      "level": "Error",
      "type": "indent"
    },
    {
      "file": "/unique_chucks/41/0xc1746273c53b9bf2d827b01b3974113bb597eaeb.sol",
      "line": "15",
      "column": "3",
      "message": "Expected indentation of 4 spaces but found 2",
      "level": "Error",
      "type": "indent"
    },
    {
      "file": "/unique_chucks/41/0xc1746273c53b9bf2d827b01b3974113bb597eaeb.sol",
      "line": "17",
      "column": "3",
      "message": "Expected indentation of 4 spaces but found 2",
      "level": "Error",
      "type": "indent"
    },
    {
      "file": "/unique_chucks/41/0xc1746273c53b9bf2d827b01b3974113bb597eaeb.sol",
      "line": "23",
      "column": "5",
      "message": "Expected indentation of 8 spaces but found 4",
      "level": "Error",
      "type": "indent"
    },
    {
      "file": "/unique_chucks/41/0xc1746273c53b9bf2d827b01b3974113bb597eaeb.sol",
      "line": "24",
      "column": "5",
      "message": "Expected indentation of 8 spaces but found 4",
      "level": "Error",
      "type": "indent"
    },
    {
      "file": "/unique_chucks/41/0xc1746273c53b9bf2d827b01b3974113bb597eaeb.sol",
      "line": "25",
      "column": "5",
      "message": "Expected indentation of 8 spaces but found 4",
      "level": "Error",
      "type": "indent"
    },
    {
      "file": "/unique_chucks/41/0xc1746273c53b9bf2d827b01b3974113bb597eaeb.sol",
      "line": "26",
      "column": "5",
      "message": "Expected indentation of 8 spaces but found 4",
      "level": "Error",
      "type": "indent"
    },
    {
      "file": "/unique_chucks/41/0xc1746273c53b9bf2d827b01b3974113bb597eaeb.sol",
      "line": "27",
      "column": "5",
      "message": "Expected indentation of 8 spaces but found 4",
      "level": "Error",
      "type": "indent"
    },
    {
      "file": "/unique_chucks/41/0xc1746273c53b9bf2d827b01b3974113bb597eaeb.sol",
      "line": "28",
      "column": "3",
      "message": "Expected indentation of 4 spaces but found 2",
      "level": "Error",
      "type": "indent"
    },
    {
      "file": "/unique_chucks/41/0xc1746273c53b9bf2d827b01b3974113bb597eaeb.sol",
      "line": "30",
      "column": "3",
      "message": "Expected indentation of 4 spaces but found 2",
      "level": "Error",
      "type": "indent"
    },
    {
      "file": "/unique_chucks/41/0xc1746273c53b9bf2d827b01b3974113bb597eaeb.sol",
      "line": "31",
      "column": "5",
      "message": "Expected indentation of 8 spaces but found 4",
      "level": "Error",
      "type": "indent"
    },
    {
      "file": "/unique_chucks/41/0xc1746273c53b9bf2d827b01b3974113bb597eaeb.sol",
      "line": "32",
      "column": "5",
      "message": "Expected indentation of 8 spaces but found 4",
      "level": "Error",
      "type": "indent"
    },
    {
      "file": "/unique_chucks/41/0xc1746273c53b9bf2d827b01b3974113bb597eaeb.sol",
      "line": "33",
      "column": "5",
      "message": "Expected indentation of 8 spaces but found 4",
      "level": "Error",
      "type": "indent"
    },
    {
      "file": "/unique_chucks/41/0xc1746273c53b9bf2d827b01b3974113bb597eaeb.sol",
      "line": "34",
      "column": "5",
      "message": "Expected indentation of 8 spaces but found 4",
      "level": "Error",
      "type": "indent"
    },
    {
      "file": "/unique_chucks/41/0xc1746273c53b9bf2d827b01b3974113bb597eaeb.sol",
      "line": "35",
      "column": "5",
      "message": "Expected indentation of 8 spaces but found 4",
      "level": "Error",
      "type": "indent"
    },
    {
      "file": "/unique_chucks/41/0xc1746273c53b9bf2d827b01b3974113bb597eaeb.sol",
      "line": "36",
      "column": "5",
      "message": "Expected indentation of 8 spaces but found 4",
      "level": "Error",
      "type": "indent"
    },
    {
      "file": "/unique_chucks/41/0xc1746273c53b9bf2d827b01b3974113bb597eaeb.sol",
      "line": "37",
      "column": "3",
      "message": "Expected indentation of 4 spaces but found 2",
      "level": "Error",
      "type": "indent"
    },
    {
      "file": "/unique_chucks/41/0xc1746273c53b9bf2d827b01b3974113bb597eaeb.sol",
      "line": "39",
      "column": "3",
      "message": "Expected indentation of 4 spaces but found 2",
      "level": "Error",
      "type": "indent"
    },
    {
      "file": "/unique_chucks/41/0xc1746273c53b9bf2d827b01b3974113bb597eaeb.sol",
      "line": "41",
      "column": "5",
      "message": "Expected indentation of 8 spaces but found 4",
      "level": "Error",
      "type": "indent"
    },
    {
      "file": "/unique_chucks/41/0xc1746273c53b9bf2d827b01b3974113bb597eaeb.sol",
      "line": "42",
      "column": "5",
      "message": "Expected indentation of 8 spaces but found 4",
      "level": "Error",
      "type": "indent"
    },
    {
      "file": "/unique_chucks/41/0xc1746273c53b9bf2d827b01b3974113bb597eaeb.sol",
      "line": "43",
      "column": "5",
      "message": "Expected indentation of 8 spaces but found 4",
      "level": "Error",
      "type": "indent"
    },
    {
      "file": "/unique_chucks/41/0xc1746273c53b9bf2d827b01b3974113bb597eaeb.sol",
      "line": "44",
      "column": "3",
      "message": "Expected indentation of 4 spaces but found 2",
      "level": "Error",
      "type": "indent"
    },
    {
      "file": "/unique_chucks/41/0xc1746273c53b9bf2d827b01b3974113bb597eaeb.sol",
      "line": "46",
      "column": "3",
      "message": "Expected indentation of 4 spaces but found 2",
      "level": "Error",
      "type": "indent"
    },
    {
      "file": "/unique_chucks/41/0xc1746273c53b9bf2d827b01b3974113bb597eaeb.sol",
      "line": "47",
      "column": "5",
      "message": "Expected indentation of 8 spaces but found 4",
      "level": "Error",
      "type": "indent"
    },
    {
      "file": "/unique_chucks/41/0xc1746273c53b9bf2d827b01b3974113bb597eaeb.sol",
      "line": "48",
      "column": "5",
      "message": "Expected indentation of 8 spaces but found 4",
      "level": "Error",
      "type": "indent"
    },
    {
      "file": "/unique_chucks/41/0xc1746273c53b9bf2d827b01b3974113bb597eaeb.sol",
      "line": "49",
      "column": "5",
      "message": "Expected indentation of 8 spaces but found 4",
      "level": "Error",
      "type": "indent"
    },
    {
      "file": "/unique_chucks/41/0xc1746273c53b9bf2d827b01b3974113bb597eaeb.sol",
      "line": "50",
      "column": "5",
      "message": "Expected indentation of 8 spaces but found 4",
      "level": "Error",
      "type": "indent"
    },
    {
      "file": "/unique_chucks/41/0xc1746273c53b9bf2d827b01b3974113bb597eaeb.sol",
      "line": "51",
      "column": "5",
      "message": "Expected indentation of 8 spaces but found 4",
      "level": "Error",
      "type": "indent"
    },
    {
      "file": "/unique_chucks/41/0xc1746273c53b9bf2d827b01b3974113bb597eaeb.sol",
      "line": "52",
      "column": "5",
      "message": "Expected indentation of 8 spaces but found 4",
      "level": "Error",
      "type": "indent"
    },
    {
      "file": "/unique_chucks/41/0xc1746273c53b9bf2d827b01b3974113bb597eaeb.sol",
      "line": "53",
      "column": "5",
      "message": "Expected indentation of 8 spaces but found 4",
      "level": "Error",
      "type": "indent"
    },
    {
      "file": "/unique_chucks/41/0xc1746273c53b9bf2d827b01b3974113bb597eaeb.sol",
      "line": "54",
      "column": "5",
      "message": "Expected indentation of 8 spaces but found 4",
      "level": "Error",
      "type": "indent"
    },
    {
      "file": "/unique_chucks/41/0xc1746273c53b9bf2d827b01b3974113bb597eaeb.sol",
      "line": "55",
      "column": "3",
      "message": "Expected indentation of 4 spaces but found 2",
      "level": "Error",
      "type": "indent"
    }
  ]
}