{
  "contract": "0xfd9768d92ce58866507a547ae400ef800e5da18d",
  "tool": "oyente",
  "start": 1563477062.4998553,
  "end": 1563477083.729415,
  "duration": 21.229559659957886,
  "analysis": [
    {
      "errors": [
        {
          "line": 32,
          "column": 5,
          "level": "Warning",
          "message": "Integer Underflow."
        },
        {
          "line": 26,
          "column": 17,
          "level": "Warning",
          "message": "Integer Overflow."
        }
      ],
      "file": "/unique_chucks/3/0xfd9768d92ce58866507a547ae400ef800e5da18d.sol",
      "name": "Dcoin",
      "evm_code_coverage": "74.4%",
      "integer_underflow": true,
      "integer_overflow": true,
      "parity_multisig_bug_2": false,
      "callstack_depth_attack_vulnerability": false,
      "transaction-ordering_dependence_tod": false,
      "timestamp_dependency": false,
      "re-entrancy_vulnerability": false
    },
    {
      "errors": [],
      "file": "/unique_chucks/3/0xfd9768d92ce58866507a547ae400ef800e5da18d.sol",
      "name": "SafeMath",
      "evm_code_coverage": "100.0%",
      "integer_underflow": false,
      "integer_overflow": false,
      "parity_multisig_bug_2": false,
      "callstack_depth_attack_vulnerability": false,
      "transaction-ordering_dependence_tod": false,
      "timestamp_dependency": false,
      "re-entrancy_vulnerability": false
    }
  ]
}