{
  "contract": "0xbd45c1d56933bcb54099e3fff534d93d2385ee40",
  "tool": "smartcheck",
  "start": 1563749493.687577,
  "end": 1563749502.0431387,
  "duration": 8.35556173324585,
  "analysis": [
    {
      "name": "SOLIDITY_ERC20_APPROVE",
      "patternId": "af782c",
      "severity": 2,
      "line": 94,
      "column": 4,
      "content": "functionapprove(address_spender,uint256_value)publicreturns(boolsuccess){require(_value>0);allowance[msg.sender][_spender]=_value;returntrue;}"
    },
    {
      "name": "SOLIDITY_PRAGMAS_VERSION",
      "patternId": "23fc32",
      "severity": 1,
      "line": 1,
      "column": 16,
      "content": "^"
    }
  ]
}